{
  "name": "Orcish Oriflamme",
  "lang": "",
  "price": {
    "nm": "699.99",
    "ex": "559.99",
    "foil_nm": "",
    "foil_ex": ""
  },
  "currency": "$",
  "img": {
    "medium": "https://www.cardkingdom.com/images/magic-the-gathering/alpha/orcish-oriflamme-11522-medium.jpg",
    "little": "https://www.cardkingdom.com/images/magic-the-gathering/alpha/orcish-oriflamme-11522-thumb.jpg"
  },
  "webLink": {
    "normal": "https://www.cardkingdom.com/mtg/alpha/orcish-oriflamme",
    "foil": ""
  }
}